ecs_tool/__init__.py
ecs_tool/cli.py
ecs_tool/context.py
ecs_tool/data_loader.py
ecs_tool/exception.py
ecs_tool/plugins/__init__.py
ecs_tool/plugins/cluster/__init__.py
ecs_tool/plugins/cluster/commands.py
ecs_tool/plugins/cluster/data.py
ecs_tool/plugins/cluster/layouts.py
ecs_tool/plugins/dashboard/__init__.py
ecs_tool/plugins/dashboard/app.py
ecs_tool/plugins/service/__init__.py
ecs_tool/plugins/service/commands.py
ecs_tool/plugins/service/data.py
ecs_tool/plugins/service/layouts.py
ecs_tool/plugins/task/__init__.py
ecs_tool/plugins/task/commands.py
ecs_tool/plugins/task/data.py
ecs_tool/plugins/task/layouts.py
ecs_tool/runner.py
ecs_tool/ui.py
ecs_tool/utils.py
ecs_tool-0.10.4.dist-info/entry_points.txt
ecs_tool-0.10.4.dist-info/LICENSE
ecs_tool-0.10.4.dist-info/WHEEL
ecs_tool-0.10.4.dist-info/METADATA
ecs_tool-0.10.4.dist-info/RECORD
